nice_duration/__init__.py
nice_duration/nice_duration.py
nice_duration-1.0.5.dist-info/licenses/LICENSE
nice_duration-1.0.5.dist-info/WHEEL
nice_duration-1.0.5.dist-info/METADATA
nice_duration-1.0.5.dist-info/RECORD
