Metadata-Version: 2.4
Name: nice-duration
Version: 1.0.5
Summary: Nice formatting of timedelta instances
Author: Tom Koelman
License-Expression: MIT-0
License-File: LICENSE
Classifier: Programming Language :: Python :: 3
Classifier: Operating System :: OS Independent
Classifier: Development Status :: 5 - Production/Stable
Classifier: Intended Audience :: Developers
Classifier: Topic :: Software Development :: Libraries :: Python Modules
Requires-Python: >=3.13
Project-URL: issues, https://github.com/tomkoelman/nice_duration/issues
Project-URL: repository, https://github.com/tomkoelman/nice_duration.git
